reflux/__init__.py
reflux/errors.py
reflux/resources.py
reflux/theme.py
reflux/engine/reflux.js
reflux/engine/reflux.min.js
reflux/engine/theme.js
reflux/engine/theme.min.js
reflux/variables/dark.txt
reflux/variables/light.txt
reflux/variables/root.txt
reflux-1.1.0.dist-info/LICENSE
reflux-1.1.0.dist-info/METADATA
reflux-1.1.0.dist-info/WHEEL
reflux-1.1.0.dist-info/top_level.txt
reflux-1.1.0.dist-info/RECORD
