Metadata-Version: 2.1
Name: reflux
Version: 1.1.0
Summary: Extensive styling and theming functionality for Replit.
Home-page: https://github.com/frissyn/Reflux
Author: frissyn
License: MIT
Project-URL: Source Code, https://github.com/frissyn/Reflux
Project-URL: Pull Requests, https://github.com/frissyn/Reflux/pulls
Project-URL: Issue Tracker, https://github.com/frissyn/Reflux/issues
Project-URL: Documentation, https://github.com/frissyn/Reflux/tree/master/docs
Platform: UNKNOWN
Classifier: License :: OSI Approved :: MIT License
Classifier: Intended Audience :: Developers
Classifier: Operating System :: OS Independent
Classifier: Programming Language :: Python :: 3.8
Classifier: Programming Language :: Python :: 3.9
Classifier: Topic :: Software Development
Requires-Python: >=3.7.0
License-File: LICENSE
Requires-Dist: pyyaml
